BMAutomation/BMAutomation.py
BMAutomation/__init__.py
BMAutomation/version.py
bmautomation-0.1.4.2.dist-info/LICENSE
bmautomation-0.1.4.2.dist-info/METADATA
bmautomation-0.1.4.2.dist-info/WHEEL
bmautomation-0.1.4.2.dist-info/top_level.txt
bmautomation-0.1.4.2.dist-info/RECORD
