Metadata-Version: 2.1
Name: bmautomation
Version: 0.1.4.2
Summary: An Automation Tool for Benchamarking Automation.
Home-page: https://github.com/YuudachiXMMY/BMAutomation
Author: YuudachiXMMY
Author-email: hwu9@uw.edu
License: UNKNOWN
Project-URL: Bug Tracker, https://github.com/YuudachiXMMY/BMAutomation/issues
Platform: UNKNOWN
Classifier: Programming Language :: Python :: 3
Classifier: License :: OSI Approved :: MIT License
Classifier: Operating System :: OS Independent
Requires-Python: >=3.6
License-File: LICENSE
Requires-Dist: pywin32
Requires-Dist: pyautogui
Requires-Dist: uiautomation
